fastband/__init__.py
fastband/__main__.py
fastband/agents/__init__.py
fastband/agents/coordination.py
fastband/agents/onboarding.py
fastband/agents/ops_log.py
fastband/backup/__init__.py
fastband/backup/alerts.py
fastband/backup/manager.py
fastband/backup/scheduler.py
fastband/cli/__init__.py
fastband/cli/backup.py
fastband/cli/main.py
fastband/cli/plugins.py
fastband/cli/tickets.py
fastband/cli/tools.py
fastband/core/__init__.py
fastband/core/config.py
fastband/core/detection.py
fastband/core/engine.py
fastband/core/events.py
fastband/core/logging.py
fastband/core/plugins.py
fastband/core/security.py
fastband/embeddings/__init__.py
fastband/embeddings/base.py
fastband/embeddings/index.py
fastband/embeddings/chunkers/__init__.py
fastband/embeddings/chunkers/base.py
fastband/embeddings/chunkers/fixed.py
fastband/embeddings/chunkers/semantic.py
fastband/embeddings/providers/__init__.py
fastband/embeddings/providers/gemini.py
fastband/embeddings/providers/ollama.py
fastband/embeddings/providers/openai.py
fastband/embeddings/storage/__init__.py
fastband/embeddings/storage/base.py
fastband/embeddings/storage/sqlite.py
fastband/hub/Dockerfile
fastband/hub/__init__.py
fastband/hub/analyzer.py
fastband/hub/chat.py
fastband/hub/exceptions.py
fastband/hub/memory.py
fastband/hub/models.py
fastband/hub/requirements.txt
fastband/hub/server.py
fastband/hub/session.py
fastband/hub/api/__init__.py
fastband/hub/api/app.py
fastband/hub/api/routes.py
fastband/hub/auth/__init__.py
fastband/hub/auth/supabase.py
fastband/hub/billing/__init__.py
fastband/hub/billing/stripe.py
fastband/hub/control_plane/__init__.py
fastband/hub/control_plane/routes.py
fastband/hub/control_plane/service.py
fastband/hub/infra/__init__.py
fastband/hub/infra/scripts/build-and-push.sh
fastband/hub/infra/scripts/deploy.sh
fastband/hub/infra/terraform/main.tf
fastband/hub/infra/terraform/variables.tf
fastband/hub/infra/terraform/environments/dev.tfvars
fastband/hub/infra/terraform/environments/production.tfvars
fastband_mcp-1.2025.12.5.dist-info/METADATA
fastband_mcp-1.2025.12.5.dist-info/WHEEL
fastband_mcp-1.2025.12.5.dist-info/entry_points.txt
fastband_mcp-1.2025.12.5.dist-info/licenses/LICENSE
fastband_mcp-1.2025.12.5.dist-info/RECORD
