Metadata-Version: 2.4
Name: fastband-mcp
Version: 1.2025.12.5
Summary: Universal AI-powered development platform - AI-agnostic MCP server with adaptive tools, ticket management, and multi-agent coordination
Project-URL: Homepage, https://github.com/RemmyCH3CK/fastband-mcp
Project-URL: Documentation, https://github.com/RemmyCH3CK/fastband-mcp#readme
Project-URL: Repository, https://github.com/RemmyCH3CK/fastband-mcp
Project-URL: Issues, https://github.com/RemmyCH3CK/fastband-mcp/issues
Author: Fastband Team
License-Expression: MIT
License-File: LICENSE
Keywords: ai,automation,claude,development,gemini,mcp,openai,tickets,tools
Classifier: Development Status :: 3 - Alpha
Classifier: Environment :: Console
Classifier: Intended Audience :: Developers
Classifier: License :: OSI Approved :: MIT License
Classifier: Operating System :: OS Independent
Classifier: Programming Language :: Python :: 3
Classifier: Programming Language :: Python :: 3.10
Classifier: Programming Language :: Python :: 3.11
Classifier: Programming Language :: Python :: 3.12
Classifier: Topic :: Software Development :: Libraries :: Python Modules
Classifier: Topic :: Software Development :: Quality Assurance
Requires-Python: >=3.10
Requires-Dist: httpx>=0.25.0
Requires-Dist: mcp>=0.9.0
Requires-Dist: pydantic>=2.0.0
Requires-Dist: pyyaml>=6.0
Requires-Dist: rich>=13.0.0
Requires-Dist: typer>=0.9.0
Provides-Extra: all-providers
Requires-Dist: anthropic>=0.18.0; extra == 'all-providers'
Requires-Dist: google-generativeai>=0.3.0; extra == 'all-providers'
Requires-Dist: ollama>=0.1.0; extra == 'all-providers'
Requires-Dist: openai>=1.0.0; extra == 'all-providers'
Provides-Extra: claude
Requires-Dist: anthropic>=0.18.0; extra == 'claude'
Provides-Extra: dev
Requires-Dist: flask>=2.0.0; extra == 'dev'
Requires-Dist: mypy>=1.5.0; extra == 'dev'
Requires-Dist: numpy>=1.24.0; extra == 'dev'
Requires-Dist: pre-commit>=3.0.0; extra == 'dev'
Requires-Dist: pytest-asyncio>=0.21.0; extra == 'dev'
Requires-Dist: pytest-cov>=4.0.0; extra == 'dev'
Requires-Dist: pytest>=7.0.0; extra == 'dev'
Requires-Dist: ruff>=0.1.0; extra == 'dev'
Provides-Extra: full
Requires-Dist: aiofiles>=23.0.0; extra == 'full'
Requires-Dist: anthropic>=0.18.0; extra == 'full'
Requires-Dist: fastapi>=0.100.0; extra == 'full'
Requires-Dist: flask>=2.0.0; extra == 'full'
Requires-Dist: google-generativeai>=0.3.0; extra == 'full'
Requires-Dist: jinja2>=3.0.0; extra == 'full'
Requires-Dist: mypy>=1.5.0; extra == 'full'
Requires-Dist: numpy>=1.24.0; extra == 'full'
Requires-Dist: ollama>=0.1.0; extra == 'full'
Requires-Dist: openai>=1.0.0; extra == 'full'
Requires-Dist: pillow>=10.0.0; extra == 'full'
Requires-Dist: playwright>=1.40.0; extra == 'full'
Requires-Dist: pre-commit>=3.0.0; extra == 'full'
Requires-Dist: psycopg2-binary>=2.9.0; extra == 'full'
Requires-Dist: pymysql>=1.1.0; extra == 'full'
Requires-Dist: pytest-asyncio>=0.21.0; extra == 'full'
Requires-Dist: pytest-cov>=4.0.0; extra == 'full'
Requires-Dist: pytest>=7.0.0; extra == 'full'
Requires-Dist: ruff>=0.1.0; extra == 'full'
Requires-Dist: uvicorn>=0.23.0; extra == 'full'
Requires-Dist: websockets>=11.0.0; extra == 'full'
Provides-Extra: gemini
Requires-Dist: google-generativeai>=0.3.0; extra == 'gemini'
Provides-Extra: hub
Requires-Dist: aiofiles>=23.0.0; extra == 'hub'
Requires-Dist: fastapi>=0.100.0; extra == 'hub'
Requires-Dist: numpy>=1.24.0; extra == 'hub'
Requires-Dist: uvicorn>=0.23.0; extra == 'hub'
Requires-Dist: websockets>=11.0.0; extra == 'hub'
Provides-Extra: mysql
Requires-Dist: pymysql>=1.1.0; extra == 'mysql'
Provides-Extra: ollama
Requires-Dist: ollama>=0.1.0; extra == 'ollama'
Provides-Extra: openai
Requires-Dist: openai>=1.0.0; extra == 'openai'
Provides-Extra: postgres
Requires-Dist: psycopg2-binary>=2.9.0; extra == 'postgres'
Provides-Extra: screenshots
Requires-Dist: pillow>=10.0.0; extra == 'screenshots'
Requires-Dist: playwright>=1.40.0; extra == 'screenshots'
Provides-Extra: web
Requires-Dist: fastapi>=0.100.0; extra == 'web'
Requires-Dist: jinja2>=3.0.0; extra == 'web'
Requires-Dist: uvicorn>=0.23.0; extra == 'web'
Requires-Dist: websockets>=11.0.0; extra == 'web'
